{
  "animateLoading": true,
  "borderRadius": "{{appsmith.theme.borderRadius.appBorderRadius}}",
  "bottomRow": 13,
  "dynamicBindingPathList": [
    {
      "key": "truncateButtonColor"
    },
    {
      "key": "fontFamily"
    },
    {
      "key": "borderRadius"
    }
  ],
  "dynamicHeight": "AUTO_HEIGHT",
  "dynamicTriggerPathList": [],
  "fontFamily": "{{appsmith.theme.fontFamily.appFont}}",
  "fontSize": "3rem",
  "fontStyle": "BOLD",
  "isLoading": false,
  "isVisible": true,
  "key": "y2j7gywmh3",
  "leftColumn": 3,
  "maxDynamicHeight": 9000,
  "minDynamicHeight": 4,
  "minWidth": 450,
  "mobileBottomRow": 8,
  "mobileLeftColumn": 1,
  "mobileRightColumn": 37,
  "mobileTopRow": 4,
  "needsErrorInfo": false,
  "originalBottomRow": 13,
  "originalTopRow": 6,
  "overflow": "NONE",
  "parentId": "7rumzwmkuv",
  "renderMode": "CANVAS",
  "responsiveBehavior": "fill",
  "rightColumn": 33,
  "shouldTruncate": false,
  "text": "75%",
  "textAlign": "LEFT",
  "textColor": "#231f20",
  "topRow": 6,
  "truncateButtonColor": "{{appsmith.theme.colors.primaryColor}}",
  "type": "TEXT_WIDGET",
  "version": 1,
  "widgetId": "atb7l2w8up",
  "widgetName": "Text15"
}